vsgmfss_fortuna/FeatureNet.py
vsgmfss_fortuna/FusionNet_b.py
vsgmfss_fortuna/FusionNet_u.py
vsgmfss_fortuna/GMFSS.py
vsgmfss_fortuna/IFNet_HDv3.py
vsgmfss_fortuna/MetricNet.py
vsgmfss_fortuna/__init__.py
vsgmfss_fortuna/softsplat.py
vsgmfss_fortuna/util.py
vsgmfss_fortuna/warplayer.py
vsgmfss_fortuna/gmflow/__init__.py
vsgmfss_fortuna/gmflow/backbone.py
vsgmfss_fortuna/gmflow/geometry.py
vsgmfss_fortuna/gmflow/gmflow.py
vsgmfss_fortuna/gmflow/matching.py
vsgmfss_fortuna/gmflow/position.py
vsgmfss_fortuna/gmflow/transformer.py
vsgmfss_fortuna/gmflow/trident_conv.py
vsgmfss_fortuna/gmflow/utils.py
vsgmfss_fortuna/models/feat_base.pkl
vsgmfss_fortuna/models/feat_union.pkl
vsgmfss_fortuna/models/flownet.pkl
vsgmfss_fortuna/models/fusionnet_base.pkl
vsgmfss_fortuna/models/fusionnet_union.pkl
vsgmfss_fortuna/models/metric_base.pkl
vsgmfss_fortuna/models/metric_union.pkl
vsgmfss_fortuna/models/rife.pkl
vsgmfss_fortuna-1.0.0.dist-info/METADATA
vsgmfss_fortuna-1.0.0.dist-info/WHEEL
vsgmfss_fortuna-1.0.0.dist-info/licenses/LICENSE
vsgmfss_fortuna-1.0.0.dist-info/RECORD
