Metadata-Version: 2.1
Name: vsgmfss_fortuna
Version: 1.0.0
Summary: GMFSS_Fortuna function for VapourSynth
Project-URL: Homepage, https://github.com/HolyWu/vs-gmfss_fortuna
Project-URL: Bug Tracker, https://github.com/HolyWu/vs-gmfss_fortuna/issues
Author-email: HolyWu <holywu@gmail.com>
License: MIT License
License-File: LICENSE
Keywords: GMFSS_Fortuna,VapourSynth
Classifier: License :: OSI Approved :: MIT License
Classifier: Operating System :: OS Independent
Classifier: Programming Language :: Python :: 3.10
Classifier: Topic :: Multimedia :: Video
Requires-Python: >=3.10
Requires-Dist: cupy-cuda11x>=12.0.0
Requires-Dist: numpy>=1.24.2
Requires-Dist: tensorrt>=8.6.0
Requires-Dist: torch-tensorrt-fx-only>=1.4.0.dev0
Requires-Dist: torch>=1.13.1
Requires-Dist: vapoursynth>=55
